superblocks_agent/__init__.py
superblocks_agent/_constant.py
superblocks_agent/_version.py
superblocks_agent/_decorator/__init__.py
superblocks_agent/_util/__init__.py
superblocks_agent/_util/convert.py
superblocks_agent/_util/decorator.py
superblocks_agent/_util/doc.py
superblocks_agent/_util/generate.py
superblocks_agent/api/Api.py
superblocks_agent/api/Config.py
superblocks_agent/api/Result.py
superblocks_agent/api/ViewMode.py
superblocks_agent/api/__init__.py
superblocks_agent/client/Client.py
superblocks_agent/client/Config.py
superblocks_agent/client/__init__.py
superblocks_agent/testing/__init__.py
superblocks_agent/testing/step/Mock.py
superblocks_agent/testing/step/Params.py
superblocks_agent/testing/step/__init__.py
superblocks_agent/types/_BaseEnum.py
superblocks_agent/types/_DictDeserializable.py
superblocks_agent/types/_DictSerializable.py
superblocks_agent/types/_Dictizable.py
superblocks_agent/types/__init__.py
superblocks_agent/types/_client.py
superblocks_agent/types/common.py
superblocks_types/__init__.py
superblocks_types/api/__init__.py
superblocks_types/api/v1/__init__.py
superblocks_types/api/v1/api_pb2.py
superblocks_types/api/v1/api_pb2_grpc.py
superblocks_types/api/v1/blocks_pb2.py
superblocks_types/api/v1/blocks_pb2_grpc.py
superblocks_types/api/v1/event_pb2.py
superblocks_types/api/v1/event_pb2_grpc.py
superblocks_types/api/v1/service_pb2.py
superblocks_types/api/v1/service_pb2_grpc.py
superblocks_types/buf/__init__.py
superblocks_types/buf/validate/__init__.py
superblocks_types/buf/validate/expression_pb2.py
superblocks_types/buf/validate/expression_pb2_grpc.py
superblocks_types/buf/validate/validate_pb2.py
superblocks_types/buf/validate/validate_pb2_grpc.py
superblocks_types/buf/validate/priv/__init__.py
superblocks_types/buf/validate/priv/private_pb2.py
superblocks_types/buf/validate/priv/private_pb2_grpc.py
superblocks_types/common/__init__.py
superblocks_types/common/v1/__init__.py
superblocks_types/common/v1/common_pb2.py
superblocks_agent-0.0.21.dist-info/LICENSE
superblocks_agent-0.0.21.dist-info/METADATA
superblocks_agent-0.0.21.dist-info/WHEEL
superblocks_agent-0.0.21.dist-info/top_level.txt
superblocks_agent-0.0.21.dist-info/RECORD
